{
  "content": "Poszukiwana dziewczyna do pokoju dwuosobowego 800zł. Poszukiwana dziewczyna do pokoju dwuosobowego w mieszkaniu 3-pokojowym. Pokój jest w całości umeblowany. Posiada dwie osobne rozkładane kanapy, dwa biurka oraz dużą szafę, dwie komody i regał. W pokoju znajduje się wyjście na balkon. Pokój zamieszkuje studentka.\n\nW mieszkaniu znajdują się także dwie łazienki oraz kuchnia z pełnym wyposażeniem (lodówka, mikrofalówka, piekarnik, kuchenka indukcyjna, zmywarka).\n\nMieszkanie jest nowe, w nowym zabudowaniu. Do dyspozycji jest komórka lokatorska oraz miejsce parkingowe w garażu.\n\nMieszkanie mieści się przy ulicy Romana Dmowskiego, 10 min od Placu Jana Pawła, 15 min od Rynku, blisko Uniwersytet Wrocławski (z dojazdem ok.10 min) oraz Politechnika Wrocławska (dojazd ok. 15 min). W okolicy mieści się supermarket TESCO, stacja benzynowa, sklep z Bio żywnością a także Mc Donald.\n\nCena pokoju 800zł wraz ze wszystkimi opłatami (prąd, gaz, woda, internet).\n\nPreferowana osoba płci żeńskiej, młoda, dbająca o porządek. ",
  "meta": {
    "subject": "roomShare",
    "flatMeterage": null,
    "roomMeterage": null,
    "rent": 400,
    "bills": 0,
    "deposit": null,
    "internetSpeed": null,
    "district": null,
    "street": "Dmowskiego",
    "roomsCount": 3,
    "flatmatesCount": null,
    "flatmatesGenders": ["female"],
    "flatmatesOccupation": ["student"],
    "preferredOccupation": null,
    "preferredGender": "female"
  }
}