{
  "content": "Wynajmę pokój! Osiedle Sun House. Witam:)\nJestem studentką i poszukuje wspólokatora do mieszkania!\nWynajmę pokój jednoosobowy na ulicy Kleczkowskiej 49B. Jest to osiedle Sun House wybudowane w marcu 2018 roku. Mieszkanie jest nowe i w pełni wyremontowane. 350m do przystanku MPK autobusowego i tramwajowego oraz 2 km do rynku. W cenę wchodzi czynsz z opłatami (+20 zl dodatkowo internet i tv).Mieszkanie znajduję się na 5 piętrze z widokiem na drzewa. W razie dalszych pytań zapraszam do wiadomości! ",
  "meta": {
    "subject": "room",
    "flatMeterage": null,
    "roomMeterage": null,
    "rent": null,
    "bills": "20",
    "deposit": null,
    "internetSpeed": null,
    "district": "Sun House",
    "street": "Kleczkowska 49B",
    "roomsCount": null,
    "flatmatesCount": 1,
    "flatmatesGenders": ["female"],
    "flatmatesOccupation": ["student"],
    "preferredOccupation": null,
    "preferredGender": null
  }
}